{
  "project_info": {
    "project_number": "564271005022",
    "project_id": "enduring-badge-332422-default-rtdb",
    "storage_bucket": "enduring-badge-332422.appspot.com"
  },
  "client": [
    {
      "client_info": {
        "mobilesdk_app_id": "1:564271005022:android:5ea76f0532f94bd41e23cf",
        "android_client_info": {
          "package_name": "com.example.splashactivity_java"
        }
      },
      "oauth_client": [
        {
          "client_id": "564271005022-d85p99j83pgri0us6uhjomvbmr8n0rjm.apps.googleusercontent.com",
          "client_type": 1,
          "android_info": {
            "package_name": "com.example.splashactivity_java",
            "certificate_hash": "c2f47e18050108d42f4bc71eea3e8f5ef83f5f3a"
          }
        },
        {
          "client_id": "564271005022-2dpbviqi8gim4m83c2kuc8bqptpn57j6.apps.googleusercontent.com",
          "client_type": 3
        }
      ],
      "api_key": [
        {
          "current_key": "AIzaSyA4aq64xBwfSB1l5HYS1AfevHaC3nAcX48"
        }
      ],
      "services": {
        "appinvite_service": {
          "other_platform_oauth_client": [
            {
              "client_id": "564271005022-2dpbviqi8gim4m83c2kuc8bqptpn57j6.apps.googleusercontent.com",
              "client_type": 3
            }
          ]
        }
      }
    }
  ],
  "configuration_version": "1"
}